flood/__init__.py
flood/api.py
flood/models.py
flood-0.6.dist-info/DESCRIPTION.rst
flood-0.6.dist-info/METADATA
flood-0.6.dist-info/RECORD
flood-0.6.dist-info/WHEEL
flood-0.6.dist-info/metadata.json
flood-0.6.dist-info/top_level.txt
tests/__init__.py
tests/tests.py
